{
  "format_version": "1.21.60",
  "minecraft:ore_feature": {
    "description": {
      "identifier": "nacht:ores/nocturium_ore"
    },
    "count": 6,
    "replace_rules": [
      {
        "places_block": "nacht:nocturium_ore",
        "may_replace": [
          {
            "name": "minecraft:stone"
          }
        ]
      },
      {
        "places_block": "nacht:deepslate_nocturium_ore",
        "may_replace": [
          {
            "name": "minecraft:deepslate"
          }
        ]
      }
    ]
  }
}
